README.txt
setup.py
mdvalo.egg-info/PKG-INFO
mdvalo.egg-info/SOURCES.txt
mdvalo.egg-info/dependency_links.txt
mdvalo.egg-info/top_level.txt
src/__init__.py
src/hbd.py