Metadata-Version: 1.0
Name: mdvalo
Version: 0.8
Summary: wish my friend a happy birthday
Home-page: UNKNOWN
Author: A.B
Author-email: alika.bitsadze@gmail.com
License: UNKNOWN
Platform: UNKNOWN
